callmebot/__init__.py
callmebot/__init__.pyi
callmebot/cmd.py
callmebot/py.typed
callmebot-1.2.9.dist-info/LICENSE
callmebot-1.2.9.dist-info/METADATA
callmebot-1.2.9.dist-info/WHEEL
callmebot-1.2.9.dist-info/entry_points.txt
callmebot-1.2.9.dist-info/top_level.txt
callmebot-1.2.9.dist-info/RECORD
